<d place="grenie" name="intro siflex " gfx="gualtus" auto="1">

<phase id="begin" next="non">
Tu n'es pas encore allé au siège de Chouettex, non ? 
</phase>

<a id="non">Ah non. C'est quoi Chouettex ? </a>

<phase id="non" next="pourq">
C'est le service postal. Toutes les chouettes que tu vois passer dans le ciel avec des paquets, c'est Chouettex ! 
</phase>

<a id="pourq">Et pourquoi je devrais aller voir Chouettex ? </a>

<phase id="pourq" next="colis" frame="happy">
Déjà, ils ont un service gratuit super pratique. Mais pour en profiter il faut aller chercher un sifflet Chouettex. 
Ca te permettra d'appeler une chouette n'importe où. Elle pourra prendre ton courrier, te livrer des objets, le journal...
</phase>

<phase id="colis" next="num">
En plus, j'ai un colis qui m'attend chez eux. Ils ne peuvent pas me le livrer ici car les fenêtres sont trop petites. %happy%Si tu pouvais en profiter pour me le ramener, ça m'arrangerait bien. 
Le numéro du colis c'est H7894-43SD. 
</phase>

<a id="num">H7894-43SD. Super facile à retenir.</a>

<phase id="num" frame="happy">
Merci ! Je te revaudrai ça.
</phase>
	
</d>